{
  "HelpText":              "Boss Mode:\n     - Single character to which all Henchmen will travel to and trade with.\n     - Make sure, that your Henchmen can get to the boss. (e.g. won't work in housing areas)\n\nHenchman Mode:\n     - Selected characters will travel each to the Boss and give/ask for configured items.\n     - If set up in System -> Settings, your char will teleport back to your given Home.\n\nTrading Modes:\n     - Give:         Will give the specified amount to the Boss.\n     - Keep:         Will keep the specified amount and give the rest to the Boss.\n     - Ask For:      Will ask the Boss for the specified amount.\n     - Ask Until:    Will ask the Boss for items until the specified amount is reached.\n     - PAR Level:    Will try to stay on the specified amount, regardless if it has to ask for or give away.",
  "TabCharacters":         "Characters",
  "TabItems":              "Items",
  "UseARItemSell":         "Use AR ItemSell",
  "TransferBossToHenchman":"Transfer Boss to Henchman World",
  "TransferBossHelp":      "If your next henchman is on another world, your boss will transfer to it and move back to exact same position where he started.\nIt won't check if you can travel to another datacenter!\n\nExample:\nStarted on Shiva in Western La Noscea at the Shop in Aleport.\nSecond Henchman on Alpha.\nYour boss will travel and then move to the exact same position on Alpha.",
  "ARSupport":             "AR Support",
  "SelectAll":             "Select All",
  "DeselectAll":           "Deselect All",
  "SelectAllShown":        "Select All Shown",
  "DeselectAllShown":      "Deselect All Shown",
  "ImportFromClipboard":   "Import from Clipboard",
  "ImportHelp":            "Import multiple characters through the following format:\n[Name1|World1,Name2|World2,Name3|World3]",
  "AddItem":               "Add Item",
  "SearchHint":            "Search...",
  "AllCategories":         "All Categories",
  "Reset":                 "Reset",
  "ColName":               "Name",
  "ColDataCenter":         "Data Center",
  "ColWorld":              "World",
  "ColAmount":             "Amount",
  "ColTradeType":          "TradeType"
}
